odoo9_addon_record_archiver-9.0.1.0.0.99.dev3-py2.7-nspkg.pth
odoo9_addon_record_archiver-9.0.1.0.0.99.dev3.dist-info/METADATA
odoo9_addon_record_archiver-9.0.1.0.0.99.dev3.dist-info/RECORD
odoo9_addon_record_archiver-9.0.1.0.0.99.dev3.dist-info/WHEEL
odoo9_addon_record_archiver-9.0.1.0.0.99.dev3.dist-info/namespace_packages.txt
odoo9_addon_record_archiver-9.0.1.0.0.99.dev3.dist-info/top_level.txt
odoo_addons/record_archiver/README.rst
odoo_addons/record_archiver/__init__.py
odoo_addons/record_archiver/__openerp__.py
odoo_addons/record_archiver/data/cron.xml
odoo_addons/record_archiver/i18n/record_archiver.pot
odoo_addons/record_archiver/models/__init__.py
odoo_addons/record_archiver/models/ir_model.py
odoo_addons/record_archiver/models/record_lifespan.py
odoo_addons/record_archiver/security/ir.model.access.csv
odoo_addons/record_archiver/static/description/icon.png
odoo_addons/record_archiver/static/src/img/icon.png
odoo_addons/record_archiver/tests/__init__.py
odoo_addons/record_archiver/tests/test_active_search.py
odoo_addons/record_archiver/tests/test_archive.py
odoo_addons/record_archiver/views/record_lifespan_view.xml
